{
    "selected_stories": [
        "adollshouse",
        "adventuresinsayingyes",
        "alternateithicatom",
        "avatar",
        "buck",
        "exorcism",
        "eyespy",
        "fromboyhoodtofatherhood",
        "hangtime",
        "haveyoumethimyet",
        "howtodraw",
        "inamoment",
        "itsabox",
        "legacy",
        "life",
        "myfirstdaywiththeyankees",
        "naked",
        "odetostepfather",
        "sloth",
        "souls",
        "stagefright",
        "swimmingwithastronauts",
        "thatthingonmyarm",
        "theclosetthatateeverything",
        "tildeath",
        "undertheinfluence",
        "wheretheressmoke"
    ],
    "train_stories": [
        "adventuresinsayingyes",
        "alternateithicatom",
        "avatar",
        "buck",
        "exorcism",
        "eyespy",
        "fromboyhoodtofatherhood",
        "howtodraw",
        "itsabox",
        "life",
        "myfirstdaywiththeyankees",
        "naked",
        "odetostepfather",
        "sloth",
        "souls",
        "stagefright",
        "thatthingonmyarm",
        "theclosetthatateeverything",
        "tildeath",
        "undertheinfluence",
        "wheretheressmoke"
    ],
    "test_stories": [
        "adollshouse",
        "hangtime",
        "haveyoumethimyet",
        "inamoment",
        "legacy",
        "swimmingwithastronauts"
    ],
    "participants": {
        "sub-UTS01": {
            "folder": "E:\\NL\\ds003020\\derivative\\data\\preprocessed_data\\sub-UTS01",
            "available_stories": [
                "adollshouse",
                "adventuresinsayingyes",
                "alternateithicatom",
                "avatar",
                "buck",
                "exorcism",
                "eyespy",
                "fromboyhoodtofatherhood",
                "hangtime",
                "haveyoumethimyet",
                "howtodraw",
                "inamoment",
                "itsabox",
                "legacy",
                "life",
                "myfirstdaywiththeyankees",
                "naked",
                "odetostepfather",
                "sloth",
                "souls",
                "stagefright",
                "swimmingwithastronauts",
                "thatthingonmyarm",
                "theclosetthatateeverything",
                "tildeath",
                "undertheinfluence",
                "wheretheressmoke"
            ],
            "train_stories": [
                "naked",
                "odetostepfather",
                "itsabox",
                "tildeath",
                "adventuresinsayingyes",
                "buck",
                "exorcism",
                "alternateithicatom",
                "myfirstdaywiththeyankees",
                "thatthingonmyarm",
                "avatar",
                "undertheinfluence",
                "theclosetthatateeverything",
                "sloth",
                "wheretheressmoke",
                "stagefright",
                "fromboyhoodtofatherhood",
                "howtodraw",
                "life",
                "souls",
                "eyespy"
            ],
            "test_stories": [
                "hangtime",
                "legacy",
                "haveyoumethimyet",
                "swimmingwithastronauts",
                "adollshouse",
                "inamoment"
            ]
        },
        "sub-UTS02": {
            "folder": "E:\\NL\\ds003020\\derivative\\data\\preprocessed_data\\sub-UTS02",
            "available_stories": [
                "adollshouse",
                "adventuresinsayingyes",
                "alternateithicatom",
                "avatar",
                "buck",
                "exorcism",
                "eyespy",
                "fromboyhoodtofatherhood",
                "hangtime",
                "haveyoumethimyet",
                "howtodraw",
                "inamoment",
                "itsabox",
                "legacy",
                "life",
                "myfirstdaywiththeyankees",
                "naked",
                "odetostepfather",
                "sloth",
                "souls",
                "stagefright",
                "swimmingwithastronauts",
                "thatthingonmyarm",
                "theclosetthatateeverything",
                "tildeath",
                "undertheinfluence",
                "wheretheressmoke"
            ],
            "train_stories": [
                "naked",
                "odetostepfather",
                "itsabox",
                "tildeath",
                "adventuresinsayingyes",
                "buck",
                "exorcism",
                "alternateithicatom",
                "myfirstdaywiththeyankees",
                "thatthingonmyarm",
                "avatar",
                "undertheinfluence",
                "theclosetthatateeverything",
                "sloth",
                "wheretheressmoke",
                "stagefright",
                "fromboyhoodtofatherhood",
                "howtodraw",
                "life",
                "souls",
                "eyespy"
            ],
            "test_stories": [
                "hangtime",
                "legacy",
                "haveyoumethimyet",
                "swimmingwithastronauts",
                "adollshouse",
                "inamoment"
            ]
        },
        "sub-UTS03": {
            "folder": "E:\\NL\\ds003020\\derivative\\data\\preprocessed_data\\sub-UTS03",
            "available_stories": [
                "adollshouse",
                "adventuresinsayingyes",
                "alternateithicatom",
                "avatar",
                "buck",
                "exorcism",
                "eyespy",
                "fromboyhoodtofatherhood",
                "hangtime",
                "haveyoumethimyet",
                "howtodraw",
                "inamoment",
                "itsabox",
                "legacy",
                "life",
                "myfirstdaywiththeyankees",
                "naked",
                "odetostepfather",
                "sloth",
                "souls",
                "stagefright",
                "swimmingwithastronauts",
                "thatthingonmyarm",
                "theclosetthatateeverything",
                "tildeath",
                "undertheinfluence",
                "wheretheressmoke"
            ],
            "train_stories": [
                "naked",
                "odetostepfather",
                "itsabox",
                "tildeath",
                "adventuresinsayingyes",
                "buck",
                "exorcism",
                "alternateithicatom",
                "myfirstdaywiththeyankees",
                "thatthingonmyarm",
                "avatar",
                "undertheinfluence",
                "theclosetthatateeverything",
                "sloth",
                "wheretheressmoke",
                "stagefright",
                "fromboyhoodtofatherhood",
                "howtodraw",
                "life",
                "souls",
                "eyespy"
            ],
            "test_stories": [
                "hangtime",
                "legacy",
                "haveyoumethimyet",
                "swimmingwithastronauts",
                "adollshouse",
                "inamoment"
            ]
        },
        "sub-UTS04": {
            "folder": "E:\\NL\\ds003020\\derivative\\data\\preprocessed_data\\sub-UTS04",
            "available_stories": [
                "adollshouse",
                "adventuresinsayingyes",
                "alternateithicatom",
                "avatar",
                "buck",
                "exorcism",
                "eyespy",
                "fromboyhoodtofatherhood",
                "hangtime",
                "haveyoumethimyet",
                "howtodraw",
                "inamoment",
                "itsabox",
                "legacy",
                "myfirstdaywiththeyankees",
                "naked",
                "odetostepfather",
                "sloth",
                "souls",
                "stagefright",
                "swimmingwithastronauts",
                "thatthingonmyarm",
                "theclosetthatateeverything",
                "tildeath",
                "undertheinfluence",
                "wheretheressmoke"
            ],
            "train_stories": [
                "naked",
                "odetostepfather",
                "itsabox",
                "tildeath",
                "adventuresinsayingyes",
                "buck",
                "exorcism",
                "alternateithicatom",
                "myfirstdaywiththeyankees",
                "thatthingonmyarm",
                "avatar",
                "undertheinfluence",
                "theclosetthatateeverything",
                "sloth",
                "wheretheressmoke",
                "stagefright",
                "fromboyhoodtofatherhood",
                "howtodraw",
                "souls",
                "eyespy"
            ],
            "test_stories": [
                "hangtime",
                "legacy",
                "haveyoumethimyet",
                "swimmingwithastronauts",
                "adollshouse",
                "inamoment"
            ]
        },
        "sub-UTS05": {
            "folder": "E:\\NL\\ds003020\\derivative\\data\\preprocessed_data\\sub-UTS05",
            "available_stories": [
                "adollshouse",
                "adventuresinsayingyes",
                "alternateithicatom",
                "avatar",
                "buck",
                "exorcism",
                "eyespy",
                "fromboyhoodtofatherhood",
                "hangtime",
                "haveyoumethimyet",
                "howtodraw",
                "inamoment",
                "itsabox",
                "legacy",
                "life",
                "myfirstdaywiththeyankees",
                "naked",
                "odetostepfather",
                "sloth",
                "souls",
                "stagefright",
                "swimmingwithastronauts",
                "thatthingonmyarm",
                "theclosetthatateeverything",
                "tildeath",
                "undertheinfluence",
                "wheretheressmoke"
            ],
            "train_stories": [
                "naked",
                "odetostepfather",
                "itsabox",
                "tildeath",
                "adventuresinsayingyes",
                "buck",
                "exorcism",
                "alternateithicatom",
                "myfirstdaywiththeyankees",
                "thatthingonmyarm",
                "avatar",
                "undertheinfluence",
                "theclosetthatateeverything",
                "sloth",
                "wheretheressmoke",
                "stagefright",
                "fromboyhoodtofatherhood",
                "howtodraw",
                "life",
                "souls",
                "eyespy"
            ],
            "test_stories": [
                "hangtime",
                "legacy",
                "haveyoumethimyet",
                "swimmingwithastronauts",
                "adollshouse",
                "inamoment"
            ]
        },
        "sub-UTS06": {
            "folder": "E:\\NL\\ds003020\\derivative\\data\\preprocessed_data\\sub-UTS06",
            "available_stories": [
                "adollshouse",
                "adventuresinsayingyes",
                "alternateithicatom",
                "avatar",
                "buck",
                "exorcism",
                "eyespy",
                "fromboyhoodtofatherhood",
                "hangtime",
                "haveyoumethimyet",
                "howtodraw",
                "inamoment",
                "itsabox",
                "legacy",
                "life",
                "myfirstdaywiththeyankees",
                "naked",
                "odetostepfather",
                "sloth",
                "souls",
                "stagefright",
                "swimmingwithastronauts",
                "thatthingonmyarm",
                "theclosetthatateeverything",
                "tildeath",
                "undertheinfluence",
                "wheretheressmoke"
            ],
            "train_stories": [
                "naked",
                "odetostepfather",
                "itsabox",
                "tildeath",
                "adventuresinsayingyes",
                "buck",
                "exorcism",
                "alternateithicatom",
                "myfirstdaywiththeyankees",
                "thatthingonmyarm",
                "avatar",
                "undertheinfluence",
                "theclosetthatateeverything",
                "sloth",
                "wheretheressmoke",
                "stagefright",
                "fromboyhoodtofatherhood",
                "howtodraw",
                "life",
                "souls",
                "eyespy"
            ],
            "test_stories": [
                "hangtime",
                "legacy",
                "haveyoumethimyet",
                "swimmingwithastronauts",
                "adollshouse",
                "inamoment"
            ]
        },
        "sub-UTS07": {
            "folder": "E:\\NL\\ds003020\\derivative\\data\\preprocessed_data\\sub-UTS07",
            "available_stories": [
                "adollshouse",
                "adventuresinsayingyes",
                "alternateithicatom",
                "avatar",
                "buck",
                "exorcism",
                "eyespy",
                "fromboyhoodtofatherhood",
                "hangtime",
                "haveyoumethimyet",
                "howtodraw",
                "inamoment",
                "itsabox",
                "legacy",
                "life",
                "myfirstdaywiththeyankees",
                "naked",
                "odetostepfather",
                "sloth",
                "souls",
                "stagefright",
                "swimmingwithastronauts",
                "thatthingonmyarm",
                "theclosetthatateeverything",
                "tildeath",
                "undertheinfluence",
                "wheretheressmoke"
            ],
            "train_stories": [
                "naked",
                "odetostepfather",
                "itsabox",
                "tildeath",
                "adventuresinsayingyes",
                "buck",
                "exorcism",
                "alternateithicatom",
                "myfirstdaywiththeyankees",
                "thatthingonmyarm",
                "avatar",
                "undertheinfluence",
                "theclosetthatateeverything",
                "sloth",
                "wheretheressmoke",
                "stagefright",
                "fromboyhoodtofatherhood",
                "howtodraw",
                "life",
                "souls",
                "eyespy"
            ],
            "test_stories": [
                "hangtime",
                "legacy",
                "haveyoumethimyet",
                "swimmingwithastronauts",
                "adollshouse",
                "inamoment"
            ]
        },
        "sub-UTS08": {
            "folder": "E:\\NL\\ds003020\\derivative\\data\\preprocessed_data\\sub-UTS08",
            "available_stories": [
                "adollshouse",
                "adventuresinsayingyes",
                "alternateithicatom",
                "avatar",
                "buck",
                "exorcism",
                "eyespy",
                "fromboyhoodtofatherhood",
                "hangtime",
                "haveyoumethimyet",
                "howtodraw",
                "inamoment",
                "itsabox",
                "legacy",
                "life",
                "myfirstdaywiththeyankees",
                "naked",
                "odetostepfather",
                "sloth",
                "souls",
                "stagefright",
                "swimmingwithastronauts",
                "thatthingonmyarm",
                "theclosetthatateeverything",
                "tildeath",
                "undertheinfluence",
                "wheretheressmoke"
            ],
            "train_stories": [
                "naked",
                "odetostepfather",
                "itsabox",
                "tildeath",
                "adventuresinsayingyes",
                "buck",
                "exorcism",
                "alternateithicatom",
                "myfirstdaywiththeyankees",
                "thatthingonmyarm",
                "avatar",
                "undertheinfluence",
                "theclosetthatateeverything",
                "sloth",
                "wheretheressmoke",
                "stagefright",
                "fromboyhoodtofatherhood",
                "howtodraw",
                "life",
                "souls",
                "eyespy"
            ],
            "test_stories": [
                "hangtime",
                "legacy",
                "haveyoumethimyet",
                "swimmingwithastronauts",
                "adollshouse",
                "inamoment"
            ]
        },
        "sub-UTS09": {
            "folder": "E:\\NL\\ds003020\\derivative\\data\\preprocessed_data\\sub-UTS09",
            "available_stories": [
                "adollshouse",
                "adventuresinsayingyes",
                "alternateithicatom",
                "avatar",
                "buck",
                "exorcism",
                "eyespy",
                "hangtime",
                "haveyoumethimyet",
                "howtodraw",
                "inamoment",
                "itsabox",
                "legacy",
                "life",
                "myfirstdaywiththeyankees",
                "naked",
                "odetostepfather",
                "sloth",
                "souls",
                "stagefright",
                "swimmingwithastronauts",
                "thatthingonmyarm",
                "theclosetthatateeverything",
                "tildeath",
                "undertheinfluence",
                "wheretheressmoke"
            ],
            "train_stories": [
                "naked",
                "odetostepfather",
                "itsabox",
                "tildeath",
                "adventuresinsayingyes",
                "buck",
                "exorcism",
                "alternateithicatom",
                "myfirstdaywiththeyankees",
                "thatthingonmyarm",
                "avatar",
                "undertheinfluence",
                "theclosetthatateeverything",
                "sloth",
                "wheretheressmoke",
                "stagefright",
                "howtodraw",
                "life",
                "souls",
                "eyespy"
            ],
            "test_stories": [
                "hangtime",
                "legacy",
                "haveyoumethimyet",
                "swimmingwithastronauts",
                "adollshouse",
                "inamoment"
            ]
        }
    }
}